evoke/examples/godfreysmith2013communication.py
evoke/examples/skyrms2010signals.py
evoke/src/__init__.py
evoke/src/calculate.py
evoke/src/common_interest.py
evoke/src/evolve.py
evoke/src/exceptions.py
evoke/src/figure.py
evoke/src/games.py
evoke/src/info.py
evoke/tests/init.py
evoke/tests/test_evolve.py
evoke/tests/test_figure.py
evoke/tests/test_games.py
evoke/tests/test_godfreysmith2013communication.py
evoke/tests/test_info.py
evoke/tests/test_skyrms2010signals.py
evoke_signals-0.1.4.dist-info/LICENSE
evoke_signals-0.1.4.dist-info/METADATA
evoke_signals-0.1.4.dist-info/WHEEL
evoke_signals-0.1.4.dist-info/RECORD
