Metadata-Version: 2.1
Name: evoke-signals
Version: 0.1.4
Summary: Signalling games in python
License: GPL-3.0-or-later
Author: Stephen Mann
Author-email: stephenfmann@gmail.com
Requires-Python: >3.8,<3.13
Classifier: License :: OSI Approved :: GNU General Public License v3 or later (GPLv3+)
Classifier: Programming Language :: Python :: 3
Classifier: Programming Language :: Python :: 3.9
Classifier: Programming Language :: Python :: 3.10
Classifier: Programming Language :: Python :: 3.11
Classifier: Programming Language :: Python :: 3.12
Requires-Dist: matplotlib (>3.7.1)
Requires-Dist: numpy (>1.20)
Requires-Dist: python-ternary (>1.0.0)
Requires-Dist: scipy (>=1.10.1,<2.0.0)
Requires-Dist: tqdm (>4.50.1)
